py_archons/__init__.py
py_archons/core.py
py_archons/helpers.py
py_archons/version.py
py_archons-0.3.3.dist-info/licenses/LICENSE
py_archons-0.3.3.dist-info/METADATA
py_archons-0.3.3.dist-info/WHEEL
py_archons-0.3.3.dist-info/top_level.txt
py_archons-0.3.3.dist-info/RECORD
