Metadata-Version: 2.4
Name: py-archons
Version: 0.3.3
Summary: A simple Python package with get_names, get_cities, and get_countries functions
Author-email: Bruno <bruno@example.com>
License-Expression: MIT
Keywords: python,package,names
Classifier: Development Status :: 3 - Alpha
Classifier: Intended Audience :: Developers
Classifier: Programming Language :: Python :: 3
Classifier: Programming Language :: Python :: 3.7
Classifier: Programming Language :: Python :: 3.8
Classifier: Programming Language :: Python :: 3.9
Classifier: Programming Language :: Python :: 3.10
Classifier: Programming Language :: Python :: 3.11
Classifier: Programming Language :: Python :: 3.12
Requires-Python: >=3.7
License-File: LICENSE
Dynamic: license-file
